{
  "project_info": {
    "project_number": "665113379424",
    "project_id": "poznan-ranking-365",
    "storage_bucket": "poznan-ranking-365.appspot.com"
  },
  "client": [
    {
      "client_info": {
        "mobilesdk_app_id": "1:665113379424:android:cc45b7d4877a160b4c7905",
        "android_client_info": {
          "package_name": "com.karolinaprzekota.poznan_ranking"
        }
      },
      "oauth_client": [
        {
          "client_id": "665113379424-cmd6164dcv6mr0tv1q9mvhl2bjhuomrm.apps.googleusercontent.com",
          "client_type": 3
        }
      ],
      "api_key": [
        {
          "current_key": "AIzaSyCvXLMxGDsBDQQkBnR92EfI5I23FZalWqg"
        }
      ],
      "services": {
        "appinvite_service": {
          "other_platform_oauth_client": [
            {
              "client_id": "665113379424-cmd6164dcv6mr0tv1q9mvhl2bjhuomrm.apps.googleusercontent.com",
              "client_type": 3
            }
          ]
        }
      }
    }
  ],
  "configuration_version": "1"
}